{"weather":{"latitude":47.6062095,"longitude":-122.3320708,"timezone":"America/Los_Angeles","currently":{"time":1506288663,"summary":"Clear","icon":"clear-day","nearestStormDistance":5,"nearestStormBearing":330,"precipIntensity":0,"precipProbability":0,"temperature":68.77,"apparentTemperature":68.77,"dewPoint":52.28,"humidity":0.56,"pressure":1020,"windSpeed":1.64,"windGust":4.84,"windBearing":331,"cloudCover":0,"uvIndex":3,"visibility":10,"ozone":308.96},"minutely":{"summary":"Clear for the hour.","icon":"clear-day","data":[{"time":1506288660,"precipIntensity":0,"precipProbability":0},{"time":1506288720,"precipIntensity":0,"precipProbability":0},{"time":1506288780,"precipIntensity":0,"precipProbability":0},{"time":1506288840,"precipIntensity":0,"precipProbability":0},{"time":1506288900,"precipIntensity":0,"precipProbability":0},{"time":1506288960,"precipIntensity":0,"precipProbability":0},{"time":1506289020,"precipIntensity":0,"precipProbability":0},{"time":1506289080,"precipIntensity":0,"precipProbability":0},{"time":1506289140,"precipIntensity":0,"precipProbability":0},{"time":1506289200,"precipIntensity":0,"precipProbability":0},{"time":1506289260,"precipIntensity":0,"precipProbability":0},{"time":1506289320,"precipIntensity":0,"precipProbability":0},{"time":1506289380,"precipIntensity":0,"precipProbability":0},{"time":1506289440,"precipIntensity":0,"precipProbability":0},{"time":1506289500,"precipIntensity":0,"precipProbability":0},{"time":1506289560,"precipIntensity":0,"precipProbability":0},{"time":1506289620,"precipIntensity":0,"precipProbability":0},{"time":1506289680,"precipIntensity":0,"precipProbability":0},{"time":1506289740,"precipIntensity":0,"precipProbability":0},{"time":1506289800,"precipIntensity":0,"precipProbability":0},{"time":1506289860,"precipIntensity":0,"precipProbability":0},{"time":1506289920,"precipIntensity":0,"precipProbability":0},{"time":1506289980,"precipIntensity":0,"precipProbability":0},{"time":1506290040,"precipIntensity":0,"precipProbability":0},{"time":1506290100,"precipIntensity":0,"precipProbability":0},{"time":1506290160,"precipIntensity":0,"precipProbability":0},{"time":1506290220,"precipIntensity":0,"precipProbability":0},{"time":1506290280,"precipIntensity":0,"precipProbability":0},{"time":1506290340,"precipIntensity":0,"precipProbability":0},{"time":1506290400,"precipIntensity":0,"precipProbability":0},{"time":1506290460,"precipIntensity":0,"precipProbability":0},{"time":1506290520,"precipIntensity":0,"precipProbability":0},{"time":1506290580,"precipIntensity":0,"precipProbability":0},{"time":1506290640,"precipIntensity":0,"precipProbability":0},{"time":1506290700,"precipIntensity":0,"precipProbability":0},{"time":1506290760,"precipIntensity":0,"precipProbability":0},{"time":1506290820,"precipIntensity":0,"precipProbability":0},{"time":1506290880,"precipIntensity":0,"precipProbability":0},{"time":1506290940,"precipIntensity":0,"precipProbability":0},{"time":1506291000,"precipIntensity":0,"precipProbability":0},{"time":1506291060,"precipIntensity":0,"precipProbability":0},{"time":1506291120,"precipIntensity":0,"precipProbability":0},{"time":1506291180,"precipIntensity":0,"precipProbability":0},{"time":1506291240,"precipIntensity":0,"precipProbability":0},{"time":1506291300,"precipIntensity":0,"precipProbability":0},{"time":1506291360,"precipIntensity":0,"precipProbability":0},{"time":1506291420,"precipIntensity":0,"precipProbability":0},{"time":1506291480,"precipIntensity":0,"precipProbability":0},{"time":1506291540,"precipIntensity":0,"precipProbability":0},{"time":1506291600,"precipIntensity":0,"precipProbability":0},{"time":1506291660,"precipIntensity":0,"precipProbability":0},{"time":1506291720,"precipIntensity":0,"precipProbability":0},{"time":1506291780,"precipIntensity":0,"precipProbability":0},{"time":1506291840,"precipIntensity":0,"precipProbability":0},{"time":1506291900,"precipIntensity":0,"precipProbability":0},{"time":1506291960,"precipIntensity":0,"precipProbability":0},{"time":1506292020,"precipIntensity":0,"precipProbability":0},{"time":1506292080,"precipIntensity":0,"precipProbability":0},{"time":1506292140,"precipIntensity":0,"precipProbability":0},{"time":1506292200,"precipIntensity":0,"precipProbability":0},{"time":1506292260,"precipIntensity":0,"precipProbability":0}]},"hourly":{"summary":"Mostly cloudy starting this evening.","icon":"partly-cloudy-night","data":[{"time":1506286800,"summary":"Clear","icon":"clear-day","precipIntensity":0,"precipProbability":0,"temperature":67.62,"apparentTemperature":67.62,"dewPoint":52.01,"humidity":0.57,"pressure":1020.31,"windSpeed":1.29,"windGust":4.46,"windBearing":312,"cloudCover":0,"uvIndex":3,"visibility":10,"ozone":309.17},{"time":1506290400,"summary":"Clear","icon":"clear-day","precipIntensity":0,"precipProbability":0,"temperature":68.77,"apparentTemperature":68.77,"dewPoint":51.49,"humidity":0.54,"pressure":1019.71,"windSpeed":2.07,"windGust":5.2,"windBearing":341,"cloudCover":0,"uvIndex":2,"visibility":10,"ozone":308.75},{"time":1506294000,"summary":"Clear","icon":"clear-day","precipIntensity":0,"precipProbability":0,"temperature":69.33,"apparentTemperature":69.33,"dewPoint":50.98,"humidity":0.52,"pressure":1019.02,"windSpeed":3.12,"windGust":5.63,"windBearing":348,"cloudCover":0.08,"uvIndex":2,"visibility":10,"ozone":307.98},{"time":1506297600,"summary":"Clear","icon":"clear-day","precipIntensity":0.0001,"precipProbability":0.01,"precipType":"rain","temperature":69.72,"apparentTemperature":69.72,"dewPoint":50.35,"humidity":0.5,"pressure":1018.66,"windSpeed":3.49,"windGust":5.21,"windBearing":356,"cloudCover":0.22,"uvIndex":1,"visibility":10,"ozone":306.92},{"time":1506301200,"summary":"Partly Cloudy","icon":"partly-cloudy-day","precipIntensity":0.0001,"precipProbability":0.01,"precipType":"rain","temperature":68.85,"apparentTemperature":68.85,"dewPoint":50.33,"humidity":0.52,"pressure":1018.73,"windSpeed":3.34,"windGust":5.24,"windBearing":358,"cloudCover":0.39,"uvIndex":0,"visibility":10,"ozone":305.44},{"time":1506304800,"summary":"Partly Cloudy","icon":"partly-cloudy-night","precipIntensity":0.0001,"precipProbability":0.01,"precipType":"rain","temperature":65.77,"apparentTemperature":65.77,"dewPoint":50.5,"humidity":0.58,"pressure":1018.99,"windSpeed":3.18,"windGust":5.61,"windBearing":3,"cloudCover":0.33,"uvIndex":0,"visibility":10,"ozone":303.6},{"time":1506308400,"summary":"Partly Cloudy","icon":"partly-cloudy-night","precipIntensity":0.0002,"precipProbability":0.01,"precipType":"rain","temperature":62.88,"apparentTemperature":62.88,"dewPoint":50.65,"humidity":0.64,"pressure":1019.21,"windSpeed":3.12,"windGust":6.03,"windBearing":19,"cloudCover":0.3,"uvIndex":0,"visibility":10,"ozone":301.95},{"time":1506312000,"summary":"Partly Cloudy","icon":"partly-cloudy-night","precipIntensity":0.0003,"precipProbability":0.02,"precipType":"rain","temperature":61.03,"apparentTemperature":61.03,"dewPoint":50.74,"humidity":0.69,"pressure":1019.27,"windSpeed":2.82,"windGust":5.33,"windBearing":29,"cloudCover":0.33,"uvIndex":0,"visibility":10,"ozone":300.48},{"time":1506315600,"summary":"Partly Cloudy","icon":"partly-cloudy-night","precipIntensity":0.0011,"precipProbability":0.05,"precipType":"rain","temperature":60.02,"apparentTemperature":60.02,"dewPoint":50.74,"humidity":0.71,"pressure":1019.23,"windSpeed":2.93,"windGust":4.6,"windBearing":43,"cloudCover":0.37,"uvIndex":0,"visibility":10,"ozone":299.13},{"time":1506319200,"summary":"Partly Cloudy","icon":"partly-cloudy-night","precipIntensity":0.0015,"precipProbability":0.07,"precipType":"rain","temperature":59.44,"apparentTemperature":59.44,"dewPoint":50.76,"humidity":0.73,"pressure":1019.21,"windSpeed":2.74,"windGust":4.06,"windBearing":66,"cloudCover":0.43,"uvIndex":0,"visibility":10,"ozone":298.28},{"time":1506322800,"summary":"Mostly Cloudy","icon":"partly-cloudy-night","precipIntensity":0.0001,"precipProbability":0.02,"precipType":"rain","temperature":59.46,"apparentTemperature":59.46,"dewPoint":50.81,"humidity":0.73,"pressure":1019.37,"windSpeed":2.59,"windGust":3.73,"windBearing":77,"cloudCover":0.68,"uvIndex":0,"visibility":10,"ozone":298.06},{"time":1506326400,"summary":"Mostly Cloudy","icon":"partly-cloudy-night","precipIntensity":0.0001,"precipProbability":0.01,"precipType":"rain","temperature":59.42,"apparentTemperature":59.42,"dewPoint":51.04,"humidity":0.74,"pressure":1019.54,"windSpeed":1.23,"windGust":3.74,"windBearing":85,"cloudCover":0.88,"uvIndex":0,"visibility":10,"ozone":298.31},{"time":1506330000,"summary":"Mostly Cloudy","icon":"partly-cloudy-night","precipIntensity":0.0002,"precipProbability":0.02,"precipType":"rain","temperature":59.11,"apparentTemperature":59.11,"dewPoint":51.28,"humidity":0.75,"pressure":1019.65,"windSpeed":1.26,"windGust":4.66,"windBearing":72,"cloudCover":0.88,"uvIndex":0,"visibility":10,"ozone":298.45},{"time":1506333600,"summary":"Mostly Cloudy","icon":"partly-cloudy-night","precipIntensity":0.0005,"precipProbability":0.04,"precipType":"rain","temperature":58.47,"apparentTemperature":58.47,"dewPoint":51.46,"humidity":0.78,"pressure":1019.72,"windSpeed":2.32,"windGust":5.67,"windBearing":98,"cloudCover":0.78,"uvIndex":0,"visibility":9.64,"ozone":298.32},{"time":1506337200,"summary":"Overcast","icon":"cloudy","precipIntensity":0.0003,"precipProbability":0.03,"precipType":"rain","temperature":58.12,"apparentTemperature":58.12,"dewPoint":51,"humidity":0.77,"pressure":1019.69,"windSpeed":2.18,"windGust":5.06,"windBearing":93,"cloudCover":1,"uvIndex":0,"visibility":10,"ozone":298.06},{"time":1506340800,"summary":"Overcast","icon":"cloudy","precipIntensity":0.0006,"precipProbability":0.04,"precipType":"rain","temperature":57.91,"apparentTemperature":57.91,"dewPoint":51.2,"humidity":0.78,"pressure":1019.68,"windSpeed":1.77,"windGust":5.13,"windBearing":90,"cloudCover":1,"uvIndex":0,"visibility":10,"ozone":298.19},{"time":1506344400,"summary":"Mostly Cloudy","icon":"partly-cloudy-night","precipIntensity":0.0007,"precipProbability":0.05,"precipType":"rain","temperature":57.33,"apparentTemperature":57.33,"dewPoint":51.4,"humidity":0.81,"pressure":1019.67,"windSpeed":2.1,"windGust":4.79,"windBearing":122,"cloudCover":0.93,"uvIndex":0,"visibility":10,"ozone":299.12},{"time":1506348000,"summary":"Mostly Cloudy","icon":"partly-cloudy-night","precipIntensity":0.0009,"precipProbability":0.06,"precipType":"rain","temperature":56.35,"apparentTemperature":56.35,"dewPoint":51.58,"humidity":0.84,"pressure":1019.64,"windSpeed":2.04,"windGust":4.32,"windBearing":160,"cloudCover":0.84,"uvIndex":0,"visibility":10,"ozone":300.4},{"time":1506351600,"summary":"Mostly Cloudy","icon":"partly-cloudy-day","precipIntensity":0.0013,"precipProbability":0.08,"precipType":"rain","temperature":56.17,"apparentTemperature":56.17,"dewPoint":51.88,"humidity":0.86,"pressure":1019.65,"windSpeed":2.04,"windGust":4.33,"windBearing":182,"cloudCover":0.79,"uvIndex":0,"visibility":10,"ozone":301.17},{"time":1506355200,"summary":"Mostly Cloudy","icon":"partly-cloudy-day","precipIntensity":0.0024,"precipProbability":0.12,"precipType":"rain","temperature":57.2,"apparentTemperature":57.2,"dewPoint":52.43,"humidity":0.84,"pressure":1019.78,"windSpeed":2.49,"windGust":5.27,"windBearing":180,"cloudCover":0.79,"uvIndex":1,"visibility":10,"ozone":301.04},{"time":1506358800,"summary":"Mostly Cloudy","icon":"partly-cloudy-day","precipIntensity":0.0045,"precipProbability":0.19,"precipType":"rain","temperature":59.19,"apparentTemperature":59.19,"dewPoint":53.11,"humidity":0.8,"pressure":1019.94,"windSpeed":3.12,"windGust":6.66,"windBearing":171,"cloudCover":0.83,"uvIndex":1,"visibility":10,"ozone":300.21},{"time":1506362400,"summary":"Drizzle","icon":"rain","precipIntensity":0.0061,"precipProbability":0.2,"precipType":"rain","temperature":61.2,"apparentTemperature":61.2,"dewPoint":53.7,"humidity":0.76,"pressure":1020.04,"windSpeed":3.7,"windGust":7.54,"windBearing":170,"cloudCover":0.85,"uvIndex":1,"visibility":10,"ozone":299.2},{"time":1506366000,"summary":"Mostly Cloudy","icon":"partly-cloudy-day","precipIntensity":0.0048,"precipProbability":0.16,"precipType":"rain","temperature":62.83,"apparentTemperature":62.83,"dewPoint":54.01,"humidity":0.73,"pressure":1020.04,"windSpeed":3.98,"windGust":7.38,"windBearing":178,"cloudCover":0.84,"uvIndex":2,"visibility":10,"ozone":297.78},{"time":1506369600,"summary":"Mostly Cloudy","icon":"partly-cloudy-day","precipIntensity":0.0028,"precipProbability":0.11,"precipType":"rain","temperature":64.05,"apparentTemperature":64.05,"dewPoint":54.19,"humidity":0.7,"pressure":1020,"windSpeed":4.12,"windGust":6.69,"windBearing":188,"cloudCover":0.84,"uvIndex":2,"visibility":10,"ozone":295.9},{"time":1506373200,"summary":"Mostly Cloudy","icon":"partly-cloudy-day","precipIntensity":0.0021,"precipProbability":0.08,"precipType":"rain","temperature":64.43,"apparentTemperature":64.43,"dewPoint":54.35,"humidity":0.7,"pressure":1019.89,"windSpeed":4.18,"windGust":6.15,"windBearing":196,"cloudCover":0.84,"uvIndex":2,"visibility":10,"ozone":294.57},{"time":1506376800,"summary":"Mostly Cloudy","icon":"partly-cloudy-day","precipIntensity":0.0021,"precipProbability":0.08,"precipType":"rain","temperature":64.17,"apparentTemperature":64.17,"dewPoint":54.56,"humidity":0.71,"pressure":1019.68,"windSpeed":4.3,"windGust":6.11,"windBearing":202,"cloudCover":0.88,"uvIndex":1,"visibility":10,"ozone":294.1},{"time":1506380400,"summary":"Mostly Cloudy","icon":"partly-cloudy-day","precipIntensity":0.0025,"precipProbability":0.09,"precipType":"rain","temperature":63.71,"apparentTemperature":63.71,"dewPoint":54.75,"humidity":0.73,"pressure":1019.42,"windSpeed":4.33,"windGust":6.19,"windBearing":206,"cloudCover":0.93,"uvIndex":1,"visibility":10,"ozone":294.1},{"time":1506384000,"summary":"Overcast","icon":"cloudy","precipIntensity":0.0028,"precipProbability":0.09,"precipType":"rain","temperature":63.69,"apparentTemperature":63.69,"dewPoint":54.91,"humidity":0.73,"pressure":1019.3,"windSpeed":4.26,"windGust":6.06,"windBearing":205,"cloudCover":0.96,"uvIndex":0,"visibility":10,"ozone":293.83},{"time":1506387600,"summary":"Overcast","icon":"cloudy","precipIntensity":0.002,"precipProbability":0.07,"precipType":"rain","temperature":63.32,"apparentTemperature":63.32,"dewPoint":55.05,"humidity":0.74,"pressure":1019.39,"windSpeed":3.86,"windGust":5.47,"windBearing":193,"cloudCover":0.97,"uvIndex":0,"visibility":10,"ozone":292.98},{"time":1506391200,"summary":"Overcast","icon":"cloudy","precipIntensity":0.0014,"precipProbability":0.05,"precipType":"rain","temperature":62.32,"apparentTemperature":62.32,"dewPoint":55.17,"humidity":0.77,"pressure":1019.62,"windSpeed":3.13,"windGust":4.7,"windBearing":173,"cloudCover":0.97,"uvIndex":0,"visibility":10,"ozone":291.87},{"time":1506394800,"summary":"Overcast","icon":"cloudy","precipIntensity":0.0013,"precipProbability":0.05,"precipType":"rain","temperature":61.02,"apparentTemperature":61.02,"dewPoint":55.18,"humidity":0.81,"pressure":1019.86,"windSpeed":3.13,"windGust":4.07,"windBearing":176,"cloudCover":0.95,"uvIndex":0,"visibility":10,"ozone":290.59},{"time":1506398400,"summary":"Mostly Cloudy","icon":"partly-cloudy-night","precipIntensity":0.0007,"precipProbability":0.03,"precipType":"rain","temperature":60.14,"apparentTemperature":60.14,"dewPoint":55.03,"humidity":0.83,"pressure":1020.09,"windSpeed":2.88,"windGust":3.59,"windBearing":162,"cloudCover":0.88,"uvIndex":0,"visibility":10,"ozone":289.27},{"time":1506402000,"summary":"Mostly Cloudy","icon":"partly-cloudy-night","precipIntensity":0.0002,"precipProbability":0.02,"precipType":"rain","temperature":59.73,"apparentTemperature":59.73,"dewPoint":54.78,"humidity":0.84,"pressure":1020.33,"windSpeed":2.67,"windGust":3.07,"windBearing":144,"cloudCover":0.79,"uvIndex":0,"visibility":10,"ozone":287.82},{"time":1506405600,"summary":"Mostly Cloudy","icon":"partly-cloudy-night","precipIntensity":0.0002,"precipProbability":0.02,"precipType":"rain","temperature":59.71,"apparentTemperature":59.71,"dewPoint":54.52,"humidity":0.83,"pressure":1020.55,"windSpeed":2.57,"windGust":2.73,"windBearing":139,"cloudCover":0.73,"uvIndex":0,"visibility":10,"ozone":286.41},{"time":1506409200,"summary":"Mostly Cloudy","icon":"partly-cloudy-night","precipIntensity":0.0001,"precipProbability":0.02,"precipType":"rain","temperature":59.79,"apparentTemperature":59.79,"dewPoint":54.29,"humidity":0.82,"pressure":1020.68,"windSpeed":2.3,"windGust":2.47,"windBearing":139,"cloudCover":0.74,"uvIndex":0,"visibility":10,"ozone":285.14},{"time":1506412800,"summary":"Mostly Cloudy","icon":"partly-cloudy-night","precipIntensity":0.0001,"precipProbability":0.02,"precipType":"rain","temperature":59.65,"apparentTemperature":59.65,"dewPoint":54.08,"humidity":0.82,"pressure":1020.76,"windSpeed":1.98,"windGust":2.19,"windBearing":143,"cloudCover":0.79,"uvIndex":0,"visibility":10,"ozone":283.98},{"time":1506416400,"summary":"Mostly Cloudy","icon":"partly-cloudy-night","precipIntensity":0.0001,"precipProbability":0.01,"precipType":"rain","temperature":59.24,"apparentTemperature":59.24,"dewPoint":53.89,"humidity":0.82,"pressure":1020.87,"windSpeed":1.75,"windGust":1.96,"windBearing":147,"cloudCover":0.82,"uvIndex":0,"visibility":10,"ozone":282.84},{"time":1506420000,"summary":"Mostly Cloudy","icon":"partly-cloudy-night","precipIntensity":0,"precipProbability":0,"temperature":58.74,"apparentTemperature":58.74,"dewPoint":53.7,"humidity":0.83,"pressure":1021.02,"windSpeed":1.6,"windGust":1.81,"windBearing":148,"cloudCover":0.81,"uvIndex":0,"visibility":10,"ozone":281.72},{"time":1506423600,"summary":"Mostly Cloudy","icon":"partly-cloudy-night","precipIntensity":0,"precipProbability":0,"temperature":58.53,"apparentTemperature":58.53,"dewPoint":53.53,"humidity":0.83,"pressure":1021.16,"windSpeed":1.45,"windGust":1.8,"windBearing":150,"cloudCover":0.79,"uvIndex":0,"visibility":10,"ozone":280.62},{"time":1506427200,"summary":"Mostly Cloudy","icon":"partly-cloudy-night","precipIntensity":0,"precipProbability":0,"temperature":58.28,"apparentTemperature":58.28,"dewPoint":53.42,"humidity":0.84,"pressure":1021.33,"windSpeed":1.02,"windGust":1.77,"windBearing":158,"cloudCover":0.77,"uvIndex":0,"visibility":10,"ozone":279.9},{"time":1506430800,"summary":"Mostly Cloudy","icon":"partly-cloudy-night","precipIntensity":0,"precipProbability":0,"temperature":57.58,"apparentTemperature":57.58,"dewPoint":53.3,"humidity":0.86,"pressure":1021.54,"windSpeed":0.94,"windGust":1.58,"windBearing":127,"cloudCover":0.75,"uvIndex":0,"visibility":10,"ozone":279.86},{"time":1506434400,"summary":"Mostly Cloudy","icon":"partly-cloudy-night","precipIntensity":0,"precipProbability":0,"temperature":56.51,"apparentTemperature":56.51,"dewPoint":53.25,"humidity":0.89,"pressure":1021.77,"windSpeed":0.87,"windGust":1.33,"windBearing":55,"cloudCover":0.73,"uvIndex":0,"visibility":10,"ozone":280.21},{"time":1506438000,"summary":"Mostly Cloudy","icon":"partly-cloudy-day","precipIntensity":0,"precipProbability":0,"temperature":56.53,"apparentTemperature":56.53,"dewPoint":53.46,"humidity":0.89,"pressure":1021.94,"windSpeed":0.82,"windGust":1.31,"windBearing":19,"cloudCover":0.69,"uvIndex":0,"visibility":10,"ozone":280.41},{"time":1506441600,"summary":"Mostly Cloudy","icon":"partly-cloudy-day","precipIntensity":0,"precipProbability":0,"temperature":58.27,"apparentTemperature":58.27,"dewPoint":54.22,"humidity":0.86,"pressure":1022.06,"windSpeed":1.29,"windGust":1.63,"windBearing":12,"cloudCover":0.63,"uvIndex":1,"visibility":10,"ozone":280.15},{"time":1506445200,"summary":"Partly Cloudy","icon":"partly-cloudy-day","precipIntensity":0,"precipProbability":0,"temperature":61.1,"apparentTemperature":61.1,"dewPoint":55.24,"humidity":0.81,"pressure":1022.13,"windSpeed":1.9,"windGust":2.18,"windBearing":1,"cloudCover":0.56,"uvIndex":1,"visibility":10,"ozone":279.74},{"time":1506448800,"summary":"Partly Cloudy","icon":"partly-cloudy-day","precipIntensity":0,"precipProbability":0,"temperature":63.83,"apparentTemperature":63.83,"dewPoint":55.91,"humidity":0.75,"pressure":1022.08,"windSpeed":2.47,"windGust":2.94,"windBearing":344,"cloudCover":0.46,"uvIndex":2,"visibility":10,"ozone":279.47},{"time":1506452400,"summary":"Partly Cloudy","icon":"partly-cloudy-day","precipIntensity":0,"precipProbability":0,"temperature":66.32,"apparentTemperature":66.32,"dewPoint":55.88,"humidity":0.69,"pressure":1021.84,"windSpeed":3.17,"windGust":4,"windBearing":340,"cloudCover":0.31,"uvIndex":3,"visibility":10,"ozone":279.47},{"time":1506456000,"summary":"Clear","icon":"clear-day","precipIntensity":0.0001,"precipProbability":0.01,"precipType":"rain","temperature":68.37,"apparentTemperature":68.37,"dewPoint":55.46,"humidity":0.63,"pressure":1021.5,"windSpeed":4.06,"windGust":5.35,"windBearing":344,"cloudCover":0.14,"uvIndex":3,"visibility":10,"ozone":279.64},{"time":1506459600,"summary":"Clear","icon":"clear-day","precipIntensity":0.0001,"precipProbability":0.01,"precipType":"rain","temperature":69.59,"apparentTemperature":69.59,"dewPoint":55.1,"humidity":0.6,"pressure":1021.14,"windSpeed":4.97,"windGust":6.79,"windBearing":349,"cloudCover":0.02,"uvIndex":3,"visibility":10,"ozone":279.83}]},"daily":{"summary":"Drizzle tomorrow and Saturday, with temperatures peaking at 80°F on Thursday.","icon":"rain","data":[{"time":1506236400,"summary":"Partly cloudy starting in the evening.","icon":"partly-cloudy-night","sunriseTime":1506261628,"sunsetTime":1506305073,"moonPhase":0.15,"precipIntensity":0.0002,"precipIntensityMax":0.0015,"precipIntensityMaxTime":1506319200,"precipProbability":0.14,"precipType":"rain","temperatureHigh":69.72,"temperatureHighTime":1506297600,"temperatureLow":56.17,"temperatureLowTime":1506351600,"apparentTemperatureHigh":69.72,"apparentTemperatureHighTime":1506297600,"apparentTemperatureLow":56.17,"apparentTemperatureLowTime":1506351600,"dewPoint":49.6,"humidity":0.74,"pressure":1020.25,"windSpeed":1.09,"windGust":6.03,"windGustTime":1506308400,"windBearing":8,"cloudCover":0.12,"uvIndex":4,"uvIndexTime":1506283200,"visibility":10,"ozone":303.66,"temperatureMin":48.27,"temperatureMinTime":1506261600,"temperatureMax":69.72,"temperatureMaxTime":1506297600,"apparentTemperatureMin":48.27,"apparentTemperatureMinTime":1506261600,"apparentTemperatureMax":69.72,"apparentTemperatureMaxTime":1506297600},{"time":1506322800,"summary":"Mostly cloudy throughout the day.","icon":"partly-cloudy-day","sunriseTime":1506348109,"sunsetTime":1506391349,"moonPhase":0.18,"precipIntensity":0.0017,"precipIntensityMax":0.0061,"precipIntensityMaxTime":1506362400,"precipProbability":0.34,"precipType":"rain","temperatureHigh":64.43,"temperatureHighTime":1506373200,"temperatureLow":56.51,"temperatureLowTime":1506434400,"apparentTemperatureHigh":64.43,"apparentTemperatureHighTime":1506373200,"apparentTemperatureLow":56.51,"apparentTemperatureLowTime":1506434400,"dewPoint":53.22,"humidity":0.77,"pressure":1019.77,"windSpeed":2.31,"windGust":7.54,"windGustTime":1506362400,"windBearing":168,"cloudCover":0.87,"uvIndex":2,"uvIndexTime":1506366000,"visibility":10,"ozone":295.82,"temperatureMin":56.17,"temperatureMinTime":1506351600,"temperatureMax":64.43,"temperatureMaxTime":1506373200,"apparentTemperatureMin":56.17,"apparentTemperatureMinTime":1506351600,"apparentTemperatureMax":64.43,"apparentTemperatureMaxTime":1506373200},{"time":1506409200,"summary":"Mostly cloudy until afternoon.","icon":"partly-cloudy-day","sunriseTime":1506434590,"sunsetTime":1506477625,"moonPhase":0.21,"precipIntensity":0.0001,"precipIntensityMax":0.0002,"precipIntensityMaxTime":1506470400,"precipProbability":0.07,"precipType":"rain","temperatureHigh":70.51,"temperatureHighTime":1506470400,"temperatureLow":56.04,"temperatureLowTime":1506520800,"apparentTemperatureHigh":70.51,"apparentTemperatureHighTime":1506470400,"apparentTemperatureLow":56.04,"apparentTemperatureLowTime":1506520800,"dewPoint":54.27,"humidity":0.75,"pressure":1021.24,"windSpeed":2.71,"windGust":11.94,"windGustTime":1506474000,"windBearing":2,"cloudCover":0.38,"uvIndex":3,"uvIndexTime":1506452400,"visibility":10,"ozone":280.77,"temperatureMin":56.51,"temperatureMinTime":1506434400,"temperatureMax":70.51,"temperatureMaxTime":1506470400,"apparentTemperatureMin":56.51,"apparentTemperatureMinTime":1506434400,"apparentTemperatureMax":70.51,"apparentTemperatureMaxTime":1506470400},{"time":1506495600,"summary":"Partly cloudy until afternoon.","icon":"partly-cloudy-day","sunriseTime":1506521071,"sunsetTime":1506563901,"moonPhase":0.24,"precipIntensity":0.0001,"precipIntensityMax":0.0002,"precipIntensityMaxTime":1506502800,"precipProbability":0.08,"precipType":"rain","temperatureHigh":72.35,"temperatureHighTime":1506556800,"temperatureLow":56.59,"temperatureLowTime":1506607200,"apparentTemperatureHigh":72.35,"apparentTemperatureHighTime":1506556800,"apparentTemperatureLow":56.59,"apparentTemperatureLowTime":1506607200,"dewPoint":53.8,"humidity":0.72,"pressure":1019.78,"windSpeed":5.71,"windGust":12.38,"windGustTime":1506556800,"windBearing":359,"cloudCover":0.17,"uvIndex":3,"uvIndexTime":1506538800,"visibility":10,"ozone":275.61,"temperatureMin":56.04,"temperatureMinTime":1506520800,"temperatureMax":72.35,"temperatureMaxTime":1506556800,"apparentTemperatureMin":56.04,"apparentTemperatureMinTime":1506520800,"apparentTemperatureMax":72.35,"apparentTemperatureMaxTime":1506556800},{"time":1506582000,"summary":"Mostly cloudy starting in the afternoon.","icon":"partly-cloudy-night","sunriseTime":1506607553,"sunsetTime":1506650178,"moonPhase":0.27,"precipIntensity":0,"precipIntensityMax":0.0001,"precipIntensityMaxTime":1506664800,"precipProbability":0,"temperatureHigh":79.73,"temperatureHighTime":1506639600,"temperatureLow":60.94,"temperatureLowTime":1506697200,"apparentTemperatureHigh":79.73,"apparentTemperatureHighTime":1506639600,"apparentTemperatureLow":60.94,"apparentTemperatureLowTime":1506697200,"dewPoint":52.22,"humidity":0.6,"pressure":1016.66,"windSpeed":1.76,"windGust":9.11,"windGustTime":1506643200,"windBearing":5,"cloudCover":0.31,"uvIndex":3,"uvIndexTime":1506621600,"ozone":266.36,"temperatureMin":56.59,"temperatureMinTime":1506607200,"temperatureMax":79.73,"temperatureMaxTime":1506639600,"apparentTemperatureMin":56.59,"apparentTemperatureMinTime":1506607200,"apparentTemperatureMax":79.73,"apparentTemperatureMaxTime":1506639600},{"time":1506668400,"summary":"Drizzle overnight.","icon":"rain","sunriseTime":1506694035,"sunsetTime":1506736455,"moonPhase":0.3,"precipIntensity":0.0006,"precipIntensityMax":0.0025,"precipIntensityMaxTime":1506740400,"precipProbability":0.11,"precipType":"rain","temperatureHigh":73.37,"temperatureHighTime":1506718800,"temperatureLow":57.76,"temperatureLowTime":1506783600,"apparentTemperatureHigh":73.37,"apparentTemperatureHighTime":1506718800,"apparentTemperatureLow":57.76,"apparentTemperatureLowTime":1506783600,"dewPoint":52.61,"humidity":0.62,"pressure":1016.29,"windSpeed":2.95,"windGust":9.56,"windGustTime":1506718800,"windBearing":166,"cloudCover":0.59,"uvIndex":2,"uvIndexTime":1506708000,"ozone":262.65,"temperatureMin":60.94,"temperatureMinTime":1506697200,"temperatureMax":73.37,"temperatureMaxTime":1506718800,"apparentTemperatureMin":60.94,"apparentTemperatureMinTime":1506697200,"apparentTemperatureMax":73.37,"apparentTemperatureMaxTime":1506718800},{"time":1506754800,"summary":"Drizzle in the morning.","icon":"rain","sunriseTime":1506780516,"sunsetTime":1506822732,"moonPhase":0.33,"precipIntensity":0.0023,"precipIntensityMax":0.0067,"precipIntensityMaxTime":1506762000,"precipProbability":0.27,"precipType":"rain","temperatureHigh":69.35,"temperatureHighTime":1506805200,"temperatureLow":54.64,"temperatureLowTime":1506870000,"apparentTemperatureHigh":69.35,"apparentTemperatureHighTime":1506805200,"apparentTemperatureLow":54.64,"apparentTemperatureLowTime":1506870000,"dewPoint":53.03,"humidity":0.71,"pressure":1019.78,"windSpeed":3,"windGust":6.86,"windGustTime":1506826800,"windBearing":186,"cloudCover":0.3,"uvIndex":3,"uvIndexTime":1506798000,"ozone":261.32,"temperatureMin":57.76,"temperatureMinTime":1506783600,"temperatureMax":69.35,"temperatureMaxTime":1506805200,"apparentTemperatureMin":57.76,"apparentTemperatureMinTime":1506783600,"apparentTemperatureMax":69.35,"apparentTemperatureMaxTime":1506805200},{"time":1506841200,"summary":"Light rain overnight.","icon":"rain","sunriseTime":1506866999,"sunsetTime":1506909010,"moonPhase":0.36,"precipIntensity":0.001,"precipIntensityMax":0.0029,"precipIntensityMaxTime":1506913200,"precipProbability":0.1,"precipType":"rain","temperatureHigh":64.35,"temperatureHighTime":1506891600,"temperatureLow":52.2,"temperatureLowTime":1506956400,"apparentTemperatureHigh":64.35,"apparentTemperatureHighTime":1506891600,"apparentTemperatureLow":52.2,"apparentTemperatureLowTime":1506956400,"dewPoint":49.38,"humidity":0.7,"pressure":1018.78,"windSpeed":2.17,"windGust":8.4,"windGustTime":1506909600,"windBearing":197,"cloudCover":0.64,"uvIndex":3,"uvIndexTime":1506888000,"ozone":257.8,"temperatureMin":54.64,"temperatureMinTime":1506870000,"temperatureMax":64.35,"temperatureMaxTime":1506891600,"apparentTemperatureMin":54.64,"apparentTemperatureMinTime":1506870000,"apparentTemperatureMax":64.35,"apparentTemperatureMaxTime":1506891600}]},"flags":{"sources":["isd","nearest-precip","nwspa","cmc","gfs","hrrr","madis","nam","sref","darksky"],"isd-stations":["727928-99999","727930-24233","727934-94248","727934-99999","727935-24234","727937-24222","727937-99999","727939-99999","742075-99999","742076-99999","994014-99999","994350-99999","999999-24234","999999-24244","999999-24281","999999-94290"],"units":"us"},"offset":-7},"location":"Seattle, WA, USA"}
